pyale2229kbsl/pyale2229kbsl.py
pyale2229kbsl-0.0.1.dist-info/METADATA
pyale2229kbsl-0.0.1.dist-info/WHEEL
pyale2229kbsl-0.0.1.dist-info/top_level.txt
pyale2229kbsl-0.0.1.dist-info/RECORD
