Metadata-Version: 2.1
Name: pyale2229kbsl
Version: 0.0.1
Requires-Dist: redis
Requires-Dist: requests
Requires-Dist: asyncio
Requires-Dist: urllib3
Requires-Dist: smtplib
Requires-Dist: pymongo
Requires-Dist: hashlib
Requires-Dist: w3lib
Requires-Dist: aiohttp
Requires-Dist: email
